dash_oop_components/__init__.py
dash_oop_components/_nbdev.py
dash_oop_components/cli.py
dash_oop_components/core.py
dash_oop_components-0.0.10.dist-info/LICENSE
dash_oop_components-0.0.10.dist-info/METADATA
dash_oop_components-0.0.10.dist-info/WHEEL
dash_oop_components-0.0.10.dist-info/entry_points.txt
dash_oop_components-0.0.10.dist-info/top_level.txt
dash_oop_components-0.0.10.dist-info/RECORD
