Metadata-Version: 2.1
Name: dash-oop-components
Version: 0.0.10
Summary: small library for OOP dashboard building blocks
Home-page: https://github.com/oegedijk/dash_oop_components/tree/master/
Author: Oege Dijk
Author-email: oegedijk@gmail.com
License: Apache Software License 2.0
Keywords: dash
Platform: UNKNOWN
Classifier: Development Status :: 3 - Alpha
Classifier: Intended Audience :: Developers
Classifier: License :: OSI Approved :: Apache Software License
Classifier: Natural Language :: English
Classifier: Programming Language :: Python :: 3.6
Classifier: Programming Language :: Python :: 3.7
Classifier: Programming Language :: Python :: 3.8
Requires-Python: >=3.6
Requires-Dist: dash
Requires-Dist: dash-bootstrap-components
Requires-Dist: shortuuid
Requires-Dist: oyaml
Requires-Dist: jupyter-dash
Requires-Dist: click
